[
  {
    "first_name":"Ginny",
    "last_name":"Hallam",
    "email":"ginny@ginny.com",
    "dependent": false,
    "img-url":"http://i53.photobucket.com/albums/g55/joewright333/ScreenShot2013-11-13at113901AM.png"
  },

  {
    "first_name":"Lief",
    "last_name":"Borden",
    "email":"lief@lief.com",
    "dependent": true,
    "img-url":"http://i53.photobucket.com/albums/g55/joewright333/ScreenShot2013-11-13at113901AM.png"
  },

  {
    "first_name":"Emily",
    "last_name":"Hallam",
    "email":"emily@emily.com",
    "dependent": false,
    "img-url":"http://i53.photobucket.com/albums/g55/joewright333/ScreenShot2013-11-13at113901AM.png"
  },

  {
    "first_name":"Ara",
    "last_name":"Baghdassarian",
    "email":"ara@ara.com",
    "dependent": true,
    "img-url":"http://i53.photobucket.com/albums/g55/joewright333/ScreenShot2013-11-13at113901AM.png"
  },

  {
    "first_name":"Jason",
    "last_name":"Leskiw",
    "email":"Jason@jason.com",
    "dependent": false,
    "img-url":"http://i53.photobucket.com/albums/g55/joewright333/ScreenShot2013-11-13at113901AM.png"
  },

  {
    "first_name":"Tashina",
    "last_name":"Arias",
    "email":"tashina@tashina.com",
    "dependent": false,
    "img_url":"http://i53.photobucket.com/albums/g55/joewright333/ScreenShot2013-11-13at113901AM.png"
  },

  {
    "first_name":"Rudy",
    "last_name":"Arias",
    "email":"rudy@rudy.com",
    "dependent": true,
    "img-url":"http://i53.photobucket.com/albums/g55/joewright333/ScreenShot2013-11-13at113901AM.png"
  },

  {
    "first_name":"Riley",
    "last_name":"Arias",
    "email":"riley@riley.com",
    "dependent": true,
    "img-url":"http://i53.photobucket.com/albums/g55/joewright333/ScreenShot2013-11-13at113901AM.png"
  },

  {
    "first_name":"Nathan",
    "last_name":"Hallam",
    "email":"nathan@nathan.com",
    "dependent": false,
    "img-url":"http://i53.photobucket.com/albums/g55/joewright333/ScreenShot2013-11-13at113901AM.png"
  },

  {
    "first_name":"Linnea",
    "last_name":"Hallam",
    "email":"linnea@linnea.com",
    "dependent": true,
    "img-url":"http://i53.photobucket.com/albums/g55/joewright333/ScreenShot2013-11-13at113901AM.png"
  },

  {
    "first_name":"Oscar",
    "last_name":"Hallam",
    "email":"oscar@oscar.com",
    "dependent": true,
    "img-url":"http://i53.photobucket.com/albums/g55/joewright333/ScreenShot2013-11-13at113901AM.png"
  },

  {
    "first_name":"Olivia",
    "last_name":"Hallam",
    "email":"olivia@olivia.com",
    "dependent": false,
    "img-url":"http://i53.photobucket.com/albums/g55/joewright333/ScreenShot2013-11-13at113901AM.png"
  },

  {
    "first_name":"Isac",
    "last_name":"Hallam",
    "email":"Isac@isac.com",
    "dependent": true,
    "img-url":"http://i53.photobucket.com/albums/g55/joewright333/ScreenShot2013-11-13at113901AM.png"
  },

  {
    "first_name":"Joanna",
    "last_name":"Hallam",
    "email":"Joanna@joanna.com",
    "dependent": false,
    "img-url":"http://i53.photobucket.com/albums/g55/joewright333/ScreenShot2013-11-13at113901AM.png"
  },

]